liquid/__init__.py
liquid/hook.py
liquid/io.py
liquid/node.py
liquid/pipeline.py
liquid/runner.py
liquid/test/test_liquid.py
liquid/test/test_tmp.py
shihua_liquid-0.1.dist-info/LICENSE
shihua_liquid-0.1.dist-info/METADATA
shihua_liquid-0.1.dist-info/WHEEL
shihua_liquid-0.1.dist-info/top_level.txt
shihua_liquid-0.1.dist-info/RECORD
