Metadata-Version: 2.1
Name: shihua-liquid
Version: 0.1
Summary: Liquid is a pipeline tool based on pluggy hook technology, which is mainly used for rapid construction of data science applications.
Home-page: https://github.com/redblue0216/Liquid
Author: shihua
Author-email: 15021408795@163.com
License: MIT
Platform: UNKNOWN
Requires-Python: >=3.9.12
License-File: LICENSE
